Register_File/source/reg64.v
module reg64 (
    input         clk,
    input         rst,
    input         we,
    input  [63:0] d,
    output reg [63:0] q
);
    always @(posedge clk or posedge rst) begin
        if (rst)
            q <= 64'd0;
        else if (we)
            q <= d;
    end
endmodule

Register_File/source/regfile64.v
module regfile64 (
    input         clk,
    input         rst,
    input         we,
    input  [4:0]  Rw,   // Write register address
    input  [4:0]  Ra,   // Read register A address
    input  [4:0]  Rb,   // Read register B address
    input  [63:0] W,    // Write data
    output [63:0] A,    // Read data A
    output [63:0] B,    // Read data B
    output [63:0] debug_regs [0:31] // Debug port for all registers
);
    wire [63:0] q[31:0];
    genvar i;
    // Generate 32 registers
    generate
        for (i = 0; i < 32; i = i + 1) begin : regs
            if (i == 0) begin
                // x0 is always zero
                assign q[i] = 64'd0;
            end else begin
                reg64 u_reg (
                    .clk(clk),
                    .rst(rst),
                    .we(we && (Rw == i)),
                    .d(W),
                    .q(q[i])
                );
            end
        end
    endgenerate
    // Read ports
    assign A = q[Ra];
    assign B = q[Rb];

    // Debug port: expose all registers
    genvar j;
    generate
        for (j = 0; j < 32; j = j + 1) begin : debug
            assign debug_regs[j] = q[j];
        end
    endgenerate
endmodule

Register_File/tb/regfile64_tb.v
`timescale 1ms/10us
`include "Register File/source/regfile64.v"
module regfile64_tb;
    reg clk, rst, we;
    reg [4:0] Rw, Ra, Rb;
    reg [63:0] W;
    wire [63:0] A, B;

    regfile64 dut (
        .clk(clk),
        .rst(rst),
        .we(we),
        .Rw(Rw),
        .Ra(Ra),
        .Rb(Rb),
        .W(W),
        .A(A),
        .B(B)
    );

    initial begin
        $dumpfile("regfile64_tb.vcd");
        $dumpvars(1, regfile64_tb);
        // Dump each register individually for GTKWave
        $dumpvars(0, regfile64_tb.dut.q[0]);
        $dumpvars(0, regfile64_tb.dut.q[1]);
        $dumpvars(0, regfile64_tb.dut.q[2]);
        $dumpvars(0, regfile64_tb.dut.q[3]);
        $dumpvars(0, regfile64_tb.dut.q[4]);
        $dumpvars(0, regfile64_tb.dut.q[5]);
        $dumpvars(0, regfile64_tb.dut.q[6]);
        $dumpvars(0, regfile64_tb.dut.q[7]);
        $dumpvars(0, regfile64_tb.dut.q[8]);
        $dumpvars(0, regfile64_tb.dut.q[9]);
        $dumpvars(0, regfile64_tb.dut.q[10]);
        $dumpvars(0, regfile64_tb.dut.q[11]);
        $dumpvars(0, regfile64_tb.dut.q[12]);
        $dumpvars(0, regfile64_tb.dut.q[13]);
        $dumpvars(0, regfile64_tb.dut.q[14]);
        $dumpvars(0, regfile64_tb.dut.q[15]);
        $dumpvars(0, regfile64_tb.dut.q[16]);
        $dumpvars(0, regfile64_tb.dut.q[17]);
        $dumpvars(0, regfile64_tb.dut.q[18]);
        $dumpvars(0, regfile64_tb.dut.q[19]);
        $dumpvars(0, regfile64_tb.dut.q[20]);
        $dumpvars(0, regfile64_tb.dut.q[21]);
        $dumpvars(0, regfile64_tb.dut.q[22]);
        $dumpvars(0, regfile64_tb.dut.q[23]);
        $dumpvars(0, regfile64_tb.dut.q[24]);
        $dumpvars(0, regfile64_tb.dut.q[25]);
        $dumpvars(0, regfile64_tb.dut.q[26]);
        $dumpvars(0, regfile64_tb.dut.q[27]);
        $dumpvars(0, regfile64_tb.dut.q[28]);
        $dumpvars(0, regfile64_tb.dut.q[29]);
        $dumpvars(0, regfile64_tb.dut.q[30]);
        $dumpvars(0, regfile64_tb.dut.q[31]);
        clk = 0;
        rst = 1; we = 0; Rw = 0; Ra = 0; Rb = 0; W = 64'd0; #2;
        rst = 0;
        // Write to x1
        we = 1; Rw = 5'd1; W = 64'h1111111111111111; #2;
        // Write to x2
        we = 1; Rw = 5'd2; W = 64'h2222222222222222; #2;
        // Write to x0 (should stay zero)
        we = 1; Rw = 5'd0; W = 64'hFFFFFFFFFFFFFFFF; #2;
        // Read x1 and x2
        we = 0; Ra = 5'd1; Rb = 5'd2; #2;
        $display("A = %h, B = %h", A, B);
        if (A !== 64'h1111111111111111 || B !== 64'h2222222222222222) $fatal(1, "Read failed: A = %h, B = %h", A, B);
        // Read x0
        Ra = 5'd0; Rb = 5'd0; #2;
        $display("A = %h, B = %h (should be 0)", A, B);
        if (A !== 64'd0 || B !== 64'd0) $fatal(1, "x0 not zero: A = %h, B = %h", A, B);
        $display("All regfile64 tests passed.");
        $finish;
    end

    always #1 clk = ~clk;
    initial $monitor($time, " clk=%b rst=%b we=%b Rw=%d Ra=%d Rb=%d W=%h | A=%h B=%h", clk, rst, we, Rw, Ra, Rb, W, A, B);
endmodule

Register_File/tb/regfile64_tb.vcd
$date
	Thu Nov 20 21:17:38 2025
$end
$version
	Icarus Verilog
$end
$timescale
	10us
$end
$scope module regfile64_tb $end
$var wire 64 ! B [63:0] $end
$var wire 64 " A [63:0] $end
$var reg 5 # Ra [4:0] $end
$var reg 5 $ Rb [4:0] $end
$var reg 5 % Rw [4:0] $end
$var reg 64 & W [63:0] $end
$var reg 1 ' clk $end
$var reg 1 ( rst $end
$var reg 1 ) we $end
$upscope $end
$scope module regfile64_tb $end
$scope module dut $end
$var wire 64 * \q[0] [63:0] $end
$upscope $end
$upscope $end
$scope module regfile64_tb $end
$scope module dut $end
$var wire 64 + \q[1] [63:0] $end
$upscope $end
$upscope $end
$scope module regfile64_tb $end
$scope module dut $end
$var wire 64 , \q[2] [63:0] $end
$upscope $end
$upscope $end
$scope module regfile64_tb $end
$scope module dut $end
$var wire 64 - \q[3] [63:0] $end
$upscope $end
$upscope $end
$scope module regfile64_tb $end
$scope module dut $end
$var wire 64 . \q[4] [63:0] $end
$upscope $end
$upscope $end
$scope module regfile64_tb $end
$scope module dut $end
$var wire 64 / \q[5] [63:0] $end
$upscope $end
$upscope $end
$scope module regfile64_tb $end
$scope module dut $end
$var wire 64 0 \q[6] [63:0] $end
$upscope $end
$upscope $end
$scope module regfile64_tb $end
$scope module dut $end
$var wire 64 1 \q[7] [63:0] $end
$upscope $end
$upscope $end
$scope module regfile64_tb $end
$scope module dut $end
$var wire 64 2 \q[8] [63:0] $end
$upscope $end
$upscope $end
$scope module regfile64_tb $end
$scope module dut $end
$var wire 64 3 \q[9] [63:0] $end
$upscope $end
$upscope $end
$scope module regfile64_tb $end
$scope module dut $end
$var wire 64 4 \q[10] [63:0] $end
$upscope $end
$upscope $end
$scope module regfile64_tb $end
$scope module dut $end
$var wire 64 5 \q[11] [63:0] $end
$upscope $end
$upscope $end
$scope module regfile64_tb $end
$scope module dut $end
$var wire 64 6 \q[12] [63:0] $end
$upscope $end
$upscope $end
$scope module regfile64_tb $end
$scope module dut $end
$var wire 64 7 \q[13] [63:0] $end
$upscope $end
$upscope $end
$scope module regfile64_tb $end
$scope module dut $end
$var wire 64 8 \q[14] [63:0] $end
$upscope $end
$upscope $end
$scope module regfile64_tb $end
$scope module dut $end
$var wire 64 9 \q[15] [63:0] $end
$upscope $end
$upscope $end
$scope module regfile64_tb $end
$scope module dut $end
$var wire 64 : \q[16] [63:0] $end
$upscope $end
$upscope $end
$scope module regfile64_tb $end
$scope module dut $end
$var wire 64 ; \q[17] [63:0] $end
$upscope $end
$upscope $end
$scope module regfile64_tb $end
$scope module dut $end
$var wire 64 < \q[18] [63:0] $end
$upscope $end
$upscope $end
$scope module regfile64_tb $end
$scope module dut $end
$var wire 64 = \q[19] [63:0] $end
$upscope $end
$upscope $end
$scope module regfile64_tb $end
$scope module dut $end
$var wire 64 > \q[20] [63:0] $end
$upscope $end
$upscope $end
$scope module regfile64_tb $end
$scope module dut $end
$var wire 64 ? \q[21] [63:0] $end
$upscope $end
$upscope $end
$scope module regfile64_tb $end
$scope module dut $end
$var wire 64 @ \q[22] [63:0] $end
$upscope $end
$upscope $end
$scope module regfile64_tb $end
$scope module dut $end
$var wire 64 A \q[23] [63:0] $end
$upscope $end
$upscope $end
$scope module regfile64_tb $end
$scope module dut $end
$var wire 64 B \q[24] [63:0] $end
$upscope $end
$upscope $end
$scope module regfile64_tb $end
$scope module dut $end
$var wire 64 C \q[25] [63:0] $end
$upscope $end
$upscope $end
$scope module regfile64_tb $end
$scope module dut $end
$var wire 64 D \q[26] [63:0] $end
$upscope $end
$upscope $end
$scope module regfile64_tb $end
$scope module dut $end
$var wire 64 E \q[27] [63:0] $end
$upscope $end
$upscope $end
$scope module regfile64_tb $end
$scope module dut $end
$var wire 64 F \q[28] [63:0] $end
$upscope $end
$upscope $end
$scope module regfile64_tb $end
$scope module dut $end
$var wire 64 G \q[29] [63:0] $end
$upscope $end
$upscope $end
$scope module regfile64_tb $end
$scope module dut $end
$var wire 64 H \q[30] [63:0] $end
$upscope $end
$upscope $end
$scope module regfile64_tb $end
$scope module dut $end
$var wire 64 I \q[31] [63:0] $end
$upscope $end
$upscope $end
$enddefinitions $end
$comment Show the parameter values. $end
$dumpall
$end
#0
$dumpvars
b0 I
b0 H
b0 G
b0 F
b0 E
b0 D
b0 C
b0 B
b0 A
b0 @
b0 ?
b0 >
b0 =
b0 <
b0 ;
b0 :
b0 9
b0 8
b0 7
b0 6
b0 5
b0 4
b0 3
b0 2
b0 1
b0 0
b0 /
b0 .
b0 -
b0 ,
b0 +
b0 *
0)
1(
0'
b0 &
b0 %
b0 $
b0 #
b0 "
b0 !
$end
#100
1'
#200
0'
b1000100010001000100010001000100010001000100010001000100010001 &
b1 %
1)
0(
#300
b1000100010001000100010001000100010001000100010001000100010001 +
1'
#400
0'
b10001000100010001000100010001000100010001000100010001000100010 &
b10 %
#500
b10001000100010001000100010001000100010001000100010001000100010 ,
1'
#600
0'
b1111111111111111111111111111111111111111111111111111111111111111 &
b0 %
#700
1'
#800
0'
b10001000100010001000100010001000100010001000100010001000100010 !
b10 $
b1000100010001000100010001000100010001000100010001000100010001 "
b1 #
0)
#900
1'
#1000
0'
b0 !
b0 $
b0 "
b0 #
